MANIFEST.in
README.md
setup.cfg
setup.py
django_mptt_graph.egg-info/PKG-INFO
django_mptt_graph.egg-info/SOURCES.txt
django_mptt_graph.egg-info/dependency_links.txt
django_mptt_graph.egg-info/not-zip-safe
django_mptt_graph.egg-info/top_level.txt
mptt_graph/__init__.py
mptt_graph/admin.py
mptt_graph/apps.py
mptt_graph/models.py
mptt_graph/tests.py
mptt_graph/urls.py
mptt_graph/utils.py
mptt_graph/views.py
mptt_graph/migrations/0001_initial.py
mptt_graph/migrations/__init__.py
mptt_graph/migrations/__pycache__/0001_initial.cpython-35.pyc
mptt_graph/migrations/__pycache__/0001_initial.cpython-36.pyc
mptt_graph/migrations/__pycache__/__init__.cpython-35.pyc
mptt_graph/migrations/__pycache__/__init__.cpython-36.pyc
mptt_graph/static/mptt_graph/tree.css
mptt_graph/templates/mptt_graph/index.html
mptt_graph/templates/mptt_graph/tree.html
mptt_graph/templates/mptt_graph/tree_inline.html
mptt_graph/templatetags/__init__.py
mptt_graph/templatetags/mptt_graph_tags.py
mptt_graph/templatetags/__pycache__/__init__.cpython-35.pyc
mptt_graph/templatetags/__pycache__/__init__.cpython-36.pyc
mptt_graph/templatetags/__pycache__/mptt_graph_tags.cpython-35.pyc
mptt_graph/templatetags/__pycache__/mptt_graph_tags.cpython-36.pyc