Metadata-Version: 1.1
Name: django-mptt-graph
Version: 0.3
Summary: Graphical representation of mptt models
Home-page: https://github.com/synw/django-mptt-graph
Author: synw
Author-email: synwe@yahoo.com
License: UNKNOWN
Download-URL: https://github.com/synw/django-mptt-graph/releases/tag/0.3
Keywords: django,mptt
Platform: UNKNOWN
Classifier: Development Status :: 3 - Alpha
Classifier: Framework :: Django :: 1.9
Classifier: Intended Audience :: Developers
Classifier: License :: OSI Approved :: MIT License
Classifier: Programming Language :: Python :: 2.7
